minilite/__init__.py
minilite/__version__.py
minilite/cli.py
minilite-0.0.1.post1558700235.dist-info/METADATA
minilite-0.0.1.post1558700235.dist-info/WHEEL
minilite-0.0.1.post1558700235.dist-info/top_level.txt
minilite-0.0.1.post1558700235.dist-info/RECORD
