Metadata-Version: 2.1
Name: minilite
Version: 0.0.1.post1558700235
Summary: Mini CLI-Tool for sqlite
Home-page: http://mathcoach.htwsaar.de/
Author: Hong-Phuc Bui
Author-email: hong-phuc.bui@htwsaar.de
License: MIT
Keywords: sqlite cli
Platform: UNKNOWN
Classifier: Development Status :: 3 - Alpha
Classifier: License :: OSI Approved :: MIT License
Classifier: Programming Language :: Python :: 3.6
Classifier: Programming Language :: Python :: 3.7
